contrib/__init__.py
contrib/clipper.py
geom2d/__init__.py
geom2d/arc.py
geom2d/bezier.py
geom2d/box.py
geom2d/const.py
geom2d/debug.py
geom2d/ellipse.py
geom2d/fillet.py
geom2d/line.py
geom2d/planargraph.py
geom2d/plotpath.py
geom2d/point.py
geom2d/polygon.py
geom2d/polyline.py
geom2d/py.typed
geom2d/transform2d.py
geom2d/triangle.py
geom2d/util.py
geom2d/voronoi.py
geom2d/voronoiclip.py
utl_geom2d-0.3.1.dist-info/LICENSE
utl_geom2d-0.3.1.dist-info/METADATA
utl_geom2d-0.3.1.dist-info/WHEEL
utl_geom2d-0.3.1.dist-info/top_level.txt
utl_geom2d-0.3.1.dist-info/RECORD
