Metadata-Version: 2.1
Name: utl-geom2d
Version: 0.3.1
Summary: Simple 2D geometry package
Author-email: Claude Zervas <claude@utlco.com>
License: GNU LESSER GENERAL PUBLIC LICENSE
Project-URL: repository, https://github.com/utlco/utl-geom2d
Keywords: 2d,geometry,computational geometry,bezier
Classifier: Programming Language :: Python :: 3
Requires-Python: >=3.10
License-File: LICENSE
Requires-Dist: typing-extensions
Provides-Extra: dev
Requires-Dist: pytest ; extra == 'dev'
Requires-Dist: black ; extra == 'dev'
Requires-Dist: ruff ; extra == 'dev'
Requires-Dist: pylint ; extra == 'dev'
Requires-Dist: mypy ; extra == 'dev'
Requires-Dist: numpy ; extra == 'dev'
Requires-Dist: sphinx ; extra == 'dev'
Requires-Dist: sphinx-autobuild ; extra == 'dev'
Requires-Dist: sphinx-rtd-theme ; extra == 'dev'
Provides-Extra: test
Requires-Dist: pytest ; extra == 'test'
Requires-Dist: numpy ; extra == 'test'
